setup.py
distributions_udacity/Binomialdistribution.py
distributions_udacity/Gaussiandistribution.py
distributions_udacity/Generaldistribution.py
distributions_udacity/__init__.py
distributions_udacity.egg-info/PKG-INFO
distributions_udacity.egg-info/SOURCES.txt
distributions_udacity.egg-info/dependency_links.txt
distributions_udacity.egg-info/not-zip-safe
distributions_udacity.egg-info/top_level.txt