Metadata-Version: 1.0
Name: distributions-udacity
Version: 0.0.0.1
Summary: Gaussian distributions
Home-page: UNKNOWN
Author: UNKNOWN
Author-email: UNKNOWN
License: UNKNOWN
Platform: UNKNOWN
